[
  {
    "id": "0daa3ca0b427b9349da7e7dc00101b5668972926",
    "name": "Light",
    "selectedTokenSets": {
      "primitives/colors/light/global": "enabled",
      "primitives/colors/light/toll": "enabled"
    },
    "group": "Mode"
  },
  {
    "id": "9ebd8aed52afbffc17e2666e8b4653a53498b257",
    "name": "Dark",
    "selectedTokenSets": {
      "primitives/colors/dark/global": "enabled",
      "primitives/colors/dark/toll": "enabled"
    },
    "group": "Mode"
  },
  {
    "id": "de7b392ea3a3ba7f9afc9e307bb834c9ec5e5f0c",
    "name": "Toll",
    "selectedTokenSets": {
      "themes/toll": "enabled"
    },
    "group": "Theme"
  },
  {
    "id": "541629445ef90ad5363f9e88f52a1ccb617e6f84",
    "name": "Semantic",
    "selectedTokenSets": {
      "semantic/style": "enabled",
      "semantic/color": "enabled",
      "primitives/globals": "source",
      "primitives/typography/default": "source"
    },
    "group": "Semantic"
  }
]